{
  "trials":
  [
    {"target_figure":"L14", "rot":0, "tract0":"L31", "rot0":2, "tract1":"L14", "rot1":3, "tract2":"L13", "rot2":1, "correct_figure":2, "correct_map":
        [
          [0,0,0,0,0,0,0,0,0,0,0,0,0,0,0,0],
          [0,0,0,0,0,0,0,0,0,0,0,0,0,0,0,0],
          [0,0,0,0,0,0,0,0,0,0,0,0,0,0,0,0],
          [0,0,0,0,0,0,0,0,0,0,0,0,0,0,0,0],
          [0,0,0,0,0,0,0,0,0,0,0,0,0,0,0,0],
          [0,0,0,0,0,0,0,0,0,0,0,0,0,0,0,0],
          [0,0,0,0,0,0,0,0,0,0,0,0,0,0,0,0],
          [0,0,0,0,0,0,0,0,0,0,0,0,0,0,0,0],
          [0,0,0,0,0,0,1,1,1,1,0,0,0,0,0,0],
          [0,0,0,0,0,0,1,0,0,1,0,0,0,0,0,0],
          [0,0,0,0,0,0,1,1,1,1,0,0,0,0,0,0],
          [0,0,0,0,0,0,0,0,0,0,0,0,0,0,0,0]
        ]
    },
    {"target_figure":"L41", "rot":1, "tract0":"L41", "rot0":3, "tract1":"L21", "rot1":0, "tract2":"I2a", "rot2":2, "correct_figure":0, "correct_map":
        [
          [0,0,0,0,0,0,0,0,0,0,0,0,0,0,0,0],
          [0,0,0,0,0,0,0,0,0,0,0,0,0,0,0,0],
          [0,0,0,0,0,0,0,0,0,0,0,0,0,0,0,0],
          [0,0,0,0,0,0,0,0,0,0,0,0,0,0,0,0],
          [0,0,0,0,0,0,0,0,0,0,0,0,0,0,0,0],
          [0,0,0,0,0,0,0,0,0,0,0,0,0,0,0,0],
          [0,0,0,0,0,0,0,0,0,0,0,0,0,0,0,0],
          [0,0,0,0,0,0,1,1,1,0,0,0,0,0,0,0],
          [0,0,0,0,0,0,1,0,1,0,0,0,0,0,0,0],
          [0,0,0,0,0,0,1,0,1,0,0,0,0,0,0,0],
          [0,0,0,0,0,0,1,1,1,0,0,0,0,0,0,0],
          [0,0,0,0,0,0,0,0,0,0,0,0,0,0,0,0]
        ]
    },
    {"target_figure":"C42", "rot":1, "tract0":"I3a", "rot0":3, "tract1":"L21", "rot1":2, "tract2":"I4", "rot2":0, "correct_figure":2, "correct_map":
        [
          [0,0,0,0,0,0,0,0,0,0,0,0,0,0,0,0],
          [0,0,0,0,0,0,0,0,0,0,0,0,0,0,0,0],
          [0,0,0,0,0,0,0,0,0,0,0,0,0,0,0,0],
          [0,0,0,0,0,0,0,0,0,0,0,0,0,0,0,0],
          [0,0,0,0,0,0,0,0,0,0,0,0,0,0,0,0],
          [0,0,0,0,0,0,0,0,0,0,0,0,0,0,0,0],
          [0,0,0,0,0,0,0,0,0,0,0,0,0,0,0,0],
          [0,0,0,0,0,0,1,1,1,1,0,0,0,0,0,0],
          [0,0,0,0,0,0,1,0,0,1,0,0,0,0,0,0],
          [0,0,0,0,0,0,1,0,0,1,0,0,0,0,0,0],
          [0,0,0,0,0,0,1,1,1,1,0,0,0,0,0,0],
          [0,0,0,0,0,0,0,0,0,0,0,0,0,0,0,0]
        ]
    },
    {"target_figure":"C31", "rot":0, "tract0":"I3a", "rot0":1, "tract1":"C41", "rot1":2, "tract2":"L32", "rot2":3, "correct_figure":0, "correct_map":
        [
          [0,0,0,0,0,0,0,0,0,0,0,0,0,0,0,0],
          [0,0,0,0,0,0,0,0,0,0,0,0,0,0,0,0],
          [0,0,0,0,0,0,0,0,0,0,0,0,0,0,0,0],
          [0,0,0,0,0,0,0,0,0,0,0,0,0,0,0,0],
          [0,0,0,0,0,0,0,0,0,0,0,0,0,0,0,0],
          [0,0,0,0,0,0,0,0,0,0,0,0,0,0,0,0],
          [0,0,0,0,0,0,0,0,0,0,0,0,0,0,0,0],
          [0,0,0,0,0,0,0,0,0,0,0,0,0,0,0,0],
          [0,0,0,0,0,0,0,1,1,1,0,0,0,0,0,0],
          [0,0,0,0,0,0,0,1,0,1,0,0,0,0,0,0],
          [0,0,0,0,0,0,0,1,1,1,0,0,0,0,0,0],
          [0,0,0,0,0,0,0,0,0,0,0,0,0,0,0,0]
        ]
    },
    {"target_figure":"L32", "rot":2, "tract0":"L31", "rot0":3, "tract1":"I4", "rot1":1, "tract2":"L21", "rot2":3, "correct_figure":2, "correct_map":
        [
          [0,0,0,0,0,0,0,0,0,0,0,0,0,0,0,0],
          [0,0,0,0,0,0,0,0,0,0,0,0,0,0,0,0],
          [0,0,0,0,0,0,0,0,0,0,0,0,0,0,0,0],
          [0,0,0,0,0,0,0,0,0,0,0,0,0,0,0,0],
          [0,0,0,0,0,0,0,0,0,0,0,0,0,0,0,0],
          [0,0,0,0,0,0,0,0,0,0,0,0,0,0,0,0],
          [0,0,0,0,0,0,0,0,0,0,0,0,0,0,0,0],
          [0,0,0,0,0,0,0,0,0,0,0,0,0,0,0,0],
          [0,0,0,0,0,0,1,1,1,0,0,0,0,0,0,0],
          [0,0,0,0,0,0,1,0,1,0,0,0,0,0,0,0],
          [0,0,0,0,0,0,1,1,1,0,0,0,0,0,0,0],
          [0,0,0,0,0,0,0,0,0,0,0,0,0,0,0,0]
        ]
    },
    {"target_figure":"C32", "rot":2, "tract0":"L31", "rot0":2, "tract1":"L41", "rot1":0, "tract2":"L32", "rot2":3, "correct_figure":1, "correct_map":
        [
          [0,0,0,0,0,0,0,0,0,0,0,0,0,0,0,0],
          [0,0,0,0,0,0,0,0,0,0,0,0,0,0,0,0],
          [0,0,0,0,0,0,0,0,0,0,0,0,0,0,0,0],
          [0,0,0,0,0,0,0,0,0,0,0,0,0,0,0,0],
          [0,0,0,0,0,0,0,0,0,0,0,0,0,0,0,0],
          [0,0,0,0,0,0,0,0,0,0,0,0,0,0,0,0],
          [0,0,0,0,0,0,0,0,0,0,0,0,0,0,0,0],
          [0,0,0,0,0,0,1,1,1,1,0,0,0,0,0,0],
          [0,0,0,0,0,0,1,0,0,1,0,0,0,0,0,0],
          [0,0,0,0,0,0,1,0,0,1,0,0,0,0,0,0],
          [0,0,0,0,0,0,1,1,1,1,0,0,0,0,0,0],
          [0,0,0,0,0,0,0,0,0,0,0,0,0,0,0,0]
        ]
    }
  ]
}
